{"frames": {

"enemy_die-0.png":
{
	"frame": {"x":1,"y":145,"w":53,"h":42},
	"rotated": false,
	"trimmed": true,
	"spriteSourceSize": {"x":0,"y":0,"w":53,"h":42},
	"sourceSize": {"w":60,"h":42}
},
"enemy_die-1.png":
{
	"frame": {"x":1,"y":1,"w":55,"h":37},
	"rotated": false,
	"trimmed": true,
	"spriteSourceSize": {"x":0,"y":5,"w":55,"h":37},
	"sourceSize": {"w":60,"h":42}
},
"enemy_die-2.png":
{
	"frame": {"x":1,"y":40,"w":55,"h":29},
	"rotated": false,
	"trimmed": true,
	"spriteSourceSize": {"x":5,"y":13,"w":55,"h":29},
	"sourceSize": {"w":60,"h":42}
},
"enemy_die-3.png":
{
	"frame": {"x":1,"y":121,"w":55,"h":22},
	"rotated": false,
	"trimmed": true,
	"spriteSourceSize": {"x":5,"y":20,"w":55,"h":22},
	"sourceSize": {"w":60,"h":42}
},
"enemy_die-4.png":
{
	"frame": {"x":1,"y":71,"w":55,"h":23},
	"rotated": false,
	"trimmed": true,
	"spriteSourceSize": {"x":5,"y":19,"w":55,"h":23},
	"sourceSize": {"w":60,"h":42}
},
"enemy_die-5.png":
{
	"frame": {"x":1,"y":96,"w":55,"h":23},
	"rotated": false,
	"trimmed": true,
	"spriteSourceSize": {"x":5,"y":19,"w":55,"h":23},
	"sourceSize": {"w":60,"h":42}
}},
"animations": {
	"enemy_die": ["enemy_die-0.png","enemy_die-1.png","enemy_die-2.png","enemy_die-3.png","enemy_die-4.png","enemy_die-5.png"]
},
"meta": {
	"app": "https://www.codeandweb.com/texturepacker",
	"version": "1.0",
	"image": "atlas.png",
	"format": "RGBA8888",
	"size": {"w":57,"h":188},
	"scale": "1",
	"smartupdate": "$TexturePacker:SmartUpdate:19253c6aeefdf23260eb16429b02e8d9:70c67b253dedbf710efb33894ee5567e:cbce6b53f0f49e0bf15173c25c41f876$"
}
}
